{"stats":{"minecraft:crafted":{"minecraft:black_dye":1,"minecraft:chain":5,"minecraft:blaze_powder":2,"mcwfurnitures:oak_modern_chair":1,"sophisticatedbackpacks:anvil_upgrade":1,"sophisticatedbackpacks:crafting_upgrade":3,"securitycraft:keypad_item":2,"irons_spellbooks:fire_ale":1,"securitycraft:scanner_door_item":1,"minecraft:iron_bars":16,"sophisticatedbackpacks:smelting_upgrade":3,"vanillaplustools:iron_hammer":2,"camera:image":14,"minecraft:iron_door":3,"alexsmobs:cooked_catfish":23,"redeco:spruce_chair":8,"irons_spellbooks:scroll":3,"minecraft:emerald":62,"securitycraft:reinforced_stone_button":16,"minecraft:copper_ingot":254,"minecraft:sticky_piston":1,"irons_spellbooks:arcane_anvil":1,"farmersdelight:golden_knife":1,"minecraft:iron_pickaxe":5,"sophisticatedbackpacks:auto_smelting_upgrade":1,"minecraft:iron_block":10,"minecraft:gold_ingot":204,"sophisticatedbackpacks:blasting_upgrade":1,"irons_spellbooks:mana_ring":2,"minecraft:netherite_ingot":3,"irons_spellbooks:arcane_ingot":8,"minecraft:leather_leggings":2,"minecraft:iron_nugget":36,"irons_spellbooks:wandering_magician_leggings":2,"sophisticatedbackpacks:stack_upgrade_tier_1":2,"minecraft:bone_meal":96,"irons_spellbooks:netherite_mage_leggings":1,"elevatorid:elevator_gray":5,"minecraft:spruce_stairs":76,"securitycraft:universal_block_remover":2,"minecraft:spruce_slab":48,"minecraft:stone_pickaxe":1,"irons_spellbooks:netherite_spell_book":1,"minecraft:spruce_boat":1,"minecraft:redstone_block":3,"minecraft:wheat":27,"sophisticatedbackpacks:gold_backpack":7,"minecraft:leather_helmet":1,"securitycraft:door_indestructible_iron_item":4,"minecraft:iron_shovel":1,"irons_spellbooks:wandering_magician_helmet":1,"minecraft:oak_planks":244,"ribbits:mossy_oak_planks":130,"irons_spellbooks:iron_spell_book":2,"minecraft:stone":394,"irons_spellbooks:artificer_cane":2,"minecraft:heavy_weighted_pressure_plate":2,"irons_spellbooks:netherite_mage_chestplate":1,"minecraft:hopper":3,"minecraft:chest":39,"minecraft:copper_block":9,"minecraft:ender_eye":2,"minecraft:stone_bricks":424,"securitycraft:keypad_door_item":2,"ribbits:mossy_oak_planks_slab":6,"minecraft:oak_slab":6,"sophisticatedbackpacks:backpack":4,"minecraft:crafting_table":13,"minecraft:spruce_planks":1326,"minecraft:wooden_pickaxe":1,"irons_spellbooks:furled_map":1,"minecraft:birch_planks":16,"sophisticatedbackpacks:upgrade_base":7,"portablemobs:basic_capture_cell":1,"minecraft:diamond_pickaxe":3,"minecraft:shield":2,"irons_spellbooks:pyromancer_helmet":1,"minecraft:stick":56,"sophisticatedbackpacks:diamond_backpack":4,"minecraft:iron_ingot":408,"minecraft:leather_chestplate":1,"irons_spellbooks:magic_cloth":3,"minecraft:shears":4,"sophisticatedbackpacks:advanced_pickup_upgrade":1,"securitycraft:universal_block_reinforcer_lvl1":1,"minecraft:cherry_planks":32,"minecraft:wooden_sword":1,"minecraft:raw_iron":9,"minecraft:coal":1,"irons_spellbooks:eldritch_manuscript":2,"alexscaves:dinosaur_nugget":312,"minecraft:furnace":6,"minecraft:piston":1,"sophisticatedbackpacks:stack_upgrade_starter_tier":2,"securitycraft:retinal_scanner":1,"securitycraft:keypad_frame":2,"irons_spellbooks:scroll_forge":1,"minecraft:polished_deepslate":8,"minecraft:iron_axe":5,"minecraft:iron_hoe":2,"minecraft:slime_ball":9,"sophisticatedbackpacks:stack_upgrade_tier_2":2,"sophisticatedbackpacks:iron_backpack":3,"minecraft:red_dye":2,"minecraft:crimson_planks":8,"elevatorid:elevator_white":1,"minecraft:spruce_sign":6,"minecraft:iron_sword":2,"minecraft:golden_shovel":1,"minecraft:bucket":1,"minecraft:stone_axe":1,"minecraft:amethyst_block":1,"ribbits:maraca":1,"minecraft:bread":23,"minecraft:air":0,"minecraft:oak_boat":2,"sophisticatedbackpacks:pickup_upgrade":1,"minecraft:white_wool":9,"irons_spellbooks:wandering_magician_chestplate":1,"minecraft:anvil":3,"minecraft:torch":48,"irons_spellbooks:wandering_magician_boots":1,"minecraft:firework_rocket":70},"minecraft:used":{"irons_spellbooks:inscription_table":13,"minecraft:moss_block":3,"minecraft:chiseled_deepslate":1,"minecraft:chest":112,"minecraft:ladder":2,"bakery:apple_pie_slice":3,"minecraft:spruce_slab":383,"minecraft:poppy":9,"alexscaves:primal_magma":3,"minecraft:stone":154,"minecraft:rotten_flesh":8,"bakery:strawberry_glazed_cookie":3,"securitycraft:keypad_item":4,"minecraft:cracked_deepslate_tiles":5,"minecraft:deepslate_brick_slab":99,"minecraft:spruce_boat":1,"bakery:cupcake_display":4,"minecraft:dark_oak_slab":1,"bakery:chocolate_gateau_slice":3,"minecraft:furnace":13,"minecraft:oak_sapling":4,"minecraft:cooked_cod":9,"minecraft:egg":7,"minecraft:potato":2,"call_of_yucutan:ritual_rock_tiles":1,"minecraft:damaged_anvil":7,"minecraft:diorite":33,"minecraft:spruce_door":1,"securitycraft:door_indestructible_iron_item":2,"securitycraft:reinforced_spruce_planks":1,"securitycraft:keypad_frame":2,"minecraft:wooden_pickaxe":35,"minecraft:glow_berries":7,"irons_spellbooks:electromancer_boots":1,"irons_spellbooks:tarnished_helmet":2,"redeco:crimson_display_case":4,"bakery:cake_stand":2,"graveyard:dark_iron_bars":1,"elevatorid:elevator_white":5,"minecraft:golden_apple":7,"minecraft:blast_furnace":5,"securitycraft:universal_block_remover":32,"bakery:sweetberry_cupcake":5,"samurai_dynasty:tanuki_statue":2,"minecraft:deepslate_brick_stairs":121,"irons_spellbooks:wandering_magician_leggings":1,"minecraft:deepslate_tiles":14,"relics:horse_flute":9,"irons_spellbooks:firefly_jar":1,"graveyard:incarnated_evil_music_disc":1,"minecraft:soul_lantern":5,"graveyard:dark_iron_door":1,"vampirism:dark_stone_bricks":1,"minecraft:nether_wart_block":11,"minecraft:wooden_sword":28,"vampirism:altar_cleansing":2,"minecraft:smithing_table":1,"minecraft:birch_log":34,"camera:image_frame":12,"minecraft:oak_trapdoor":1,"minecraft:oak_boat":3,"irons_spellbooks:pyromancer_boots":2,"minecraft:iron_bars":11,"minecraft:stone_sword":28,"alexscaves:amber_monolith":4,"call_of_yucutan:macuahuitl":218,"call_of_yucutan:ancient_gold":2,"minecraft:cooked_salmon":41,"bakery:breadbox":3,"minecraft:netherrack":6,"minecraft:torch":98,"minecraft:brewing_stand":2,"minecraft:anvil":1,"redeco:spruce_coffee_table":4,"alexscaves:pewen_sapling":30,"minecraft:crimson_hyphae":3,"biomesoplenty:snowblossom_sapling":11,"minecraft:golden_shovel":32,"minecraft:iron_axe":1051,"irons_spellbooks:wandering_magician_boots":1,"call_of_yucutan:solar_projector":1,"minecraft:mud_bricks":8,"minecraft:barrel":1,"minecraft:smooth_basalt":4,"bakery:strawberry_cupcake":3,"minecraft:goat_horn":1,"minecraft:beef":12,"bakery:linzer_tart_slice":3,"minecraft:cobbled_deepslate":227,"minecraft:pointed_dripstone":4,"sophisticatedbackpacks:gold_backpack":11,"minecraft:wheat_seeds":60,"alexsmobs:cooked_catfish":51,"minecraft:water_bucket":89,"minecraft:birch_planks":12,"farmersdelight:honey_glazed_ham_block":1,"minecraft:cherry_planks":26,"securitycraft:scanner_door_item":1,"minecraft:deepslate_bricks":1436,"minecraft:salmon":6,"minecraft:polished_deepslate_slab":9,"minecraft:red_bed":4,"minecraft:crafting_table":13,"brewery:corn":1,"call_of_yucutan:ritual_rock_pillar":4,"minecraft:spruce_log":159,"minecraft:oak_log":26,"minecraft:cornflower":2,"minecraft:diamond_pickaxe":334,"irons_spellbooks:netherite_mage_leggings":1,"minecraft:iron_pickaxe":1584,"alexscaves:pine_nuts":2,"minecraft:spruce_sapling":31,"ribbits:mossy_oak_door":5,"bakery:tray":1,"minecraft:cobblestone":385,"minecraft:cooked_porkchop":2,"minecraft:potion":3,"bakery:croissant":1,"minecraft:purple_bed":5,"vanillaplustools:iron_hammer":715,"minecraft:porkchop":1,"minecraft:dandelion":4,"irons_spellbooks:arcane_anvil":4,"minecraft:jukebox":1,"minecraft:cherry_sapling":1,"minecraft:iron_shovel":154,"minecraft:polished_deepslate":1,"elevatorid:elevator_gray":4,"minecraft:diamond_hoe":168,"minecraft:shield":120,"minecraft:iron_sword":820,"minecraft:iron_chestplate":3,"minecraft:spruce_leaves":34,"minecraft:mutton":4,"minecraft:carrot":16,"minecraft:deepslate_tile_slab":9,"minecraft:tuff":62,"minecraft:cyan_wool":39,"minecraft:axolotl_bucket":1,"minecraft:obsidian":10,"sophisticatedbackpacks:diamond_backpack":6,"vampirism:item_tent":1,"minecraft:lantern":10,"call_of_yucutan:reflector":1,"minecraft:packed_mud":2,"minecraft:iron_helmet":2,"alexscaves:amber":18,"farmersdelight:sweet_berry_cheesecake_slice":1,"alexscaves:pewen_log":12,"minecraft:stone_bricks":510,"minecraft:item_frame":22,"minecraft:golden_sword":37,"minecraft:red_carpet":2,"minecraft:written_book":1,"irons_spellbooks:pyromancer_chestplate":1,"minecraft:stone_pickaxe":112,"minecraft:gray_carpet":32,"minecraft:oak_planks":165,"minecraft:ender_pearl":4,"minecraft:blue_bed":2,"minecraft:white_wool":42,"graveyard:small_light_gray_urn":1,"minecraft:loom":1,"ribbits:mossy_oak_planks_slab":9,"alexscaves:cave_book":2,"minecraft:light_blue_wool":27,"redeco:spyglass_stand":3,"farmersdelight:cod_roll":2,"minecraft:black_bed":8,"minecraft:shears":357,"minecraft:dripstone_block":6,"waystones:waystone":13,"minecraft:firework_rocket":31,"bakery:chocolate_gateau":2,"minecraft:melon_slice":17,"minecraft:bread":151,"minecraft:string":1,"minecraft:cyan_bed":1,"irons_spellbooks:pyromancer_leggings":2,"minecraft:iron_door":1,"graveyard:fire_brazier":5,"minecraft:cooked_rabbit":1,"minecraft:andesite":6,"minecraft:cobweb":58,"minecraft:coarse_dirt":1,"minecraft:chain":4,"minecraft:golden_pickaxe":1,"minecraft:bone_meal":48,"minecraft:experience_bottle":7,"minecraft:oak_fence":12,"minecraft:flint_and_steel":7,"minecraft:cracked_deepslate_bricks":3,"minecraft:spruce_planks":700,"bakery:sweetberry_cake_slice":3,"securitycraft:keypad_door_item":3,"minecraft:cooked_chicken":8,"minecraft:oak_door":1,"brewery:beer_hops":1,"minecraft:spyglass":1,"minecraft:dirt":165,"bakery:waffle":3,"minecraft:spruce_stairs":173,"minecraft:cobblestone_wall":1,"minecraft:spruce_fence":200,"aquamirae:coral_lance":29,"minecraft:granite":67,"alexsmobs:maggot":1,"minecraft:iron_hoe":47,"alexscaves:limestone_spear":11,"mcwfurnitures:oak_modern_chair":2,"minecraft:oak_stairs":1,"bakery:apple_cupcake":8,"bakery:misslilitu_biscuit":7,"minecraft:iron_boots":1,"bakery:cake_display":5,"minecraft:golden_carrot":19,"call_of_yucutan:ancient_gold_pillar":3,"call_of_yucutan:ritual_rocks":30,"vampirism:cracked_dark_stone_bricks":1,"minecraft:deepslate_tile_stairs":23,"alexsmobs:banana":1,"minecraft:cooked_beef":35,"minecraft:brown_bed":1,"minecraft:enchanted_golden_apple":1,"bakery:sweetberry_cake":6,"redeco:sculk_terrarium":2,"minecraft:iron_leggings":3,"minecraft:cooked_mutton":18,"alexscaves:dinosaur_nugget":285,"irons_spellbooks:netherite_mage_chestplate":2,"minecraft:glass_bottle":4,"minecraft:polished_andesite":1,"minecraft:baked_potato":19,"minecraft:blue_wool":39,"minecraft:spruce_sign":6,"bakery:jam_roll":1,"irons_spellbooks:pyromancer_helmet":3,"minecraft:stonecutter":1,"minecraft:green_bed":5,"farmersdelight:onion":39,"minecraft:stripped_dark_oak_log":8,"graveyard:soul_fire_brazier":2,"irons_spellbooks:alchemist_cauldron":10,"minecraft:apple":9,"biomesoplenty:pink_daffodil":1,"farmersdelight:cake_slice":3,"minecraft:cracked_polished_blackstone_bricks":1,"farmersdelight:stuffed_potato":1,"redeco:spruce_chair":7,"irons_spellbooks:scroll_forge":8,"minecraft:stone_axe":95,"bakery:bun":4,"minecraft:fishing_rod":6,"minecraft:cobbled_deepslate_slab":6,"minecraft:bucket":93,"minecraft:yellow_bed":4,"call_of_yucutan:music_disc_xibalba":1,"alexsmobs:animal_dictionary":5,"minecraft:gray_wool":54,"minecraft:sculk_catalyst":1},"minecraft:picked_up":{"irons_spellbooks:arcane_anvil":3,"minecraft:iron_chestplate":9,"alexscaves:tough_hide":7,"minecraft:anvil":2,"minecraft:smithing_table":2,"artifacts:bunny_hoppers":5,"minecraft:lead":1,"biomesoplenty:red_maple_sapling":2,"minecraft:brown_bed":3,"minecraft:oak_stairs":1,"aquamirae:coral_lance":5,"irons_spellbooks:holy_rune":1,"minecraft:wither_rose":1,"minecraft:enchanted_book":3,"minecraft:golden_shovel":1,"call_of_yucutan:huracan_helmet":1,"minecraft:golden_sword":1,"minecraft:polished_deepslate":6,"minecraft:amethyst_block":3,"alexscaves:smooth_limestone":1,"call_of_yucutan:poisonous_dart":5,"relics:magic_mirror":1,"minecraft:string":157,"minecraft:dark_oak_trapdoor":1,"minecraft:red_nether_bricks":1,"minecraft:shroomlight":1,"vampirism:obi_belt":1,"minecraft:cobbled_deepslate":306,"minecraft:spruce_planks":43,"minecraft:hopper_minecart":1,"minecraft:enchanted_golden_apple":1,"minecraft:melon_slice":17,"minecraft:coal_block":13,"minecraft:mangrove_log":1,"minecraft:dark_oak_door":1,"minecraft:golden_helmet":1,"minecraft:jukebox":1,"irons_spellbooks:shriving_stone":1,"minecraft:green_bed":7,"bakery:toast":2,"call_of_yucutan:red_limestone":4,"minecraft:cherry_log":28,"irons_spellbooks:fire_rune":2,"call_of_yucutan:music_disc_xibalba":1,"bakery:chocolate_gateau":2,"minecraft:stone_sword":1,"call_of_yucutan:reflector":1,"vampirism:blood_bottle":2,"minecraft:light_blue_wool":38,"farmersdelight:onion":37,"minecraft:red_tulip":4,"minecraft:blaze_rod":6,"minecraft:iron_bars":12,"bakery:cake_display":5,"minecraft:snowball":8,"biomesoplenty:lavender":1,"minecraft:birch_log":41,"minecraft:magma_block":10,"minecraft:feather":8,"minecraft:cooked_beef":20,"minecraft:iron_door":5,"minecraft:jungle_log":2,"minecraft:smoker":1,"farmersdelight:roast_chicken_block":1,"irons_spellbooks:ruined_book":1,"minecraft:lantern":4,"artifacts:shock_pendant":6,"biomesoplenty:snowblossom_sapling":38,"stalwart_dungeons:blaze_armor_scrap":1,"irons_spellbooks:iron_spell_book":14,"minecraft:stonecutter":1,"farmersdelight:salmon_roll":1,"vampirism:altar_pillar":12,"minecraft:diamond_helmet":1,"minecraft:glowstone_dust":9,"minecraft:moss_block":11,"biomesoplenty:magic_sapling":7,"graveyard:fire_brazier":6,"irons_spellbooks:legendary_ink":4,"irons_spellbooks:frostward_ring":5,"sophisticatedbackpacks:iron_backpack":1,"minecraft:loom":2,"minecraft:red_terracotta":1,"minecraft:trapped_chest":1,"minecraft:barrel":2,"alexsmobs:animal_dictionary":1,"irons_spellbooks:evasion_elixir":1,"farmersdelight:cake_slice":3,"irons_spellbooks:ice_rune":1,"minecraft:polished_andesite":1,"minecraft:white_candle":4,"minecraft:lever":1,"samurai_dynasty:straw_hat":5,"minecraft:granite":231,"minecraft:bread":63,"minecraft:blue_banner":1,"alexsmobs:maggot":1,"call_of_yucutan:blow_gun":3,"minecraft:crimson_roots":2,"minecraft:diamond_pickaxe":2,"minecraft:spruce_leaves":94,"sophisticatedbackpacks:gold_backpack":8,"minecraft:mud":1,"minecraft:crafting_table":5,"minecraft:coarse_dirt":1,"minecraft:bee_nest":1,"alexscaves:primal_magma":10,"minecraft:nether_wart":24,"minecraft:clay_ball":6,"minecraft:golden_pickaxe":2,"minecraft:leather_leggings":2,"irons_spellbooks:tarnished_helmet":1,"samurai_dynasty:kitsune_hide":2,"bakery:sweetberry_cake":6,"mcwfurnitures:oak_modern_chair":1,"gravestone:obituary":43,"minecraft:cornflower":2,"alexsmobs:cooked_catfish":12,"camera:image_frame":15,"minecraft:red_bed":5,"beautify:lamp_jar":2,"artifacts:power_glove":6,"minecraft:netherite_scrap":2,"minecraft:iron_shovel":2,"graveyard:soul_fire_brazier":2,"irons_spellbooks:pyromancer_leggings":2,"minecraft:beef":61,"bakery:misslilitu_biscuit":9,"minecraft:cyan_wool":39,"minecraft:iron_nugget":29,"minecraft:poppy":7,"minecraft:spruce_slab":17,"minecraft:minecart":2,"alexscaves:amber_monolith":7,"minecraft:chest":23,"minecraft:birch_sapling":3,"minecraft:raw_copper_block":2,"minecraft:egg":11,"bakery:linzer_tart_slice":3,"minecraft:sandstone":15,"minecraft:polished_deepslate_slab":11,"securitycraft:reinforced_cobblestone":8,"bakery:strawberry_cupcake":3,"minecraft:oak_door":1,"minecraft:glow_item_frame":1,"sophisticatedbackpacks:backpack":5,"minecraft:spruce_fence":18,"werewolves:raw_silver":31,"graveyard:dark_iron_bars":1,"minecraft:carrot":4,"minecraft:redstone":166,"irons_spellbooks:alchemist_cauldron":11,"samurai_dynasty:spirit_flame":1,"minecraft:deepslate_bricks":226,"minecraft:shears":1,"relics:arrow_quiver":1,"minecraft:hay_block":6,"minecraft:cracked_deepslate_bricks":12,"minecraft:gold_ingot":9,"minecraft:polished_blackstone":1,"minecraft:glow_berries":5,"minecraft:mutton":13,"minecraft:white_wool":77,"minecraft:rail":8,"minecraft:stripped_oak_log":21,"vampirism:vampire_blood_bottle":5,"minecraft:mud_bricks":10,"alexscaves:pewen_log":183,"vampirism:item_tent":2,"irons_spellbooks:pyromancer_helmet":1,"redeco:sculk_terrarium":1,"samurai_dynasty:jade":6,"minecraft:fern":1,"irons_spellbooks:netherite_spell_book":9,"minecraft:red_mushroom":5,"bakery:cornet":7,"minecraft:packed_mud":3,"graveyard:small_light_gray_urn":7,"minecraft:oak_log":177,"minecraft:lily_pad":5,"minecraft:ancient_debris":3,"minecraft:paper":178,"minecraft:blue_bed":2,"vanillaplustools:iron_hammer":1,"minecraft:white_banner":1,"alexscaves:pewen_sapling":33,"minecraft:apple":6,"minecraft:stone_bricks":157,"alexscaves:cooked_dinosaur_chop":25,"irons_spellbooks:blood_vial":2,"biomesoplenty:maple_log":3,"vampirism:cracked_dark_stone_bricks":1,"minecraft:stone_pickaxe":1,"minecraft:cobweb":36,"biomesoplenty:magic_log":19,"minecraft:glass_bottle":10,"bakery:jam_roll":2,"minecraft:iron_sword":4,"redeco:spruce_chair":1,"elevatorid:elevator_white":5,"irons_spellbooks:pyromancer_chestplate":2,"minecraft:smooth_basalt":5,"minecraft:dark_oak_slab":2,"minecraft:sweet_berries":32,"vampirism:fire_place":1,"minecraft:spyglass":1,"minecraft:gravel":6,"minecraft:spruce_sapling":72,"minecraft:spruce_log":49,"irons_spellbooks:scroll_forge":7,"minecraft:crying_obsidian":2,"minecraft:leather_helmet":1,"samurai_dynasty:oni_horn":2,"farmersdelight:stuffed_potato":1,"minecraft:purple_bed":5,"vampirism:blood_container":1,"elevatorid:elevator_gray":2,"vampirism:dark_stone_bricks":5,"alexscaves:pine_nuts":43,"minecraft:gray_wool":101,"graveyard:incarnated_evil_music_disc":1,"minecraft:warped_roots":1,"securitycraft:keypad":2,"minecraft:melon_seeds":8,"minecraft:stripped_dark_oak_log":23,"call_of_yucutan:macuahuitl":1,"minecraft:ender_pearl":3,"irons_spellbooks:scroll":5,"minecraft:chiseled_deepslate":3,"minecraft:wheat":68,"securitycraft:keypad_item":2,"bakery:apple_pie_slice":3,"minecraft:potion":6,"minecraft:nether_brick":6,"irons_spellbooks:cast_time_ring":9,"irons_spellbooks:nature_rune":1,"minecraft:raw_copper":262,"minecraft:iron_leggings":5,"minecraft:sticky_piston":1,"minecraft:armor_stand":1,"alexsmobs:blood_sac":5,"irons_spellbooks:arcane_essence":38,"minecraft:deepslate_tiles":52,"alexsmobs:banana":1,"minecraft:comparator":1,"securitycraft:reinforced_spruce_planks":1,"minecraft:rose_bush":8,"minecraft:redstone_torch":1,"minecraft:calcite":5,"minecraft:iron_pickaxe":8,"mcwwindows:stripped_oak_pane_window":1,"irons_spellbooks:inscription_table":15,"minecraft:iron_boots":6,"minecraft:furnace":10,"minecraft:blue_wool":62,"minecraft:stick":49,"minecraft:oak_fence":15,"minecraft:polished_deepslate_stairs":2,"minecraft:torch":23,"alexscaves:limestone_pillar":3,"minecraft:spruce_stairs":41,"alexscaves:heavy_bone":6,"minecraft:porkchop":7,"minecraft:target":1,"vampirism:vampire_fang":4,"minecraft:pointed_dripstone":12,"minecraft:diorite":103,"bakery:breadbox":3,"samurai_dynasty:spirit_upgrade_smithing_template":6,"minecraft:rotten_flesh":57,"irons_spellbooks:greater_invisibility_elixir":1,"bakery:cake_stand":2,"graveyard:gray_urn":1,"bakery:waffle":4,"minecraft:deepslate_brick_stairs":9,"minecraft:obsidian":10,"irons_spellbooks:cooldown_ring":1,"minecraft:cobblestone":1965,"minecraft:crimson_hyphae":5,"vampirism:vampire_book":1,"minecraft:lilac":5,"minecraft:repeater":2,"minecraft:cherry_planks":11,"minecraft:andesite":15,"minecraft:black_bed":7,"minecraft:potato":19,"irons_spellbooks:pyromancer_boots":2,"minecraft:tuff":224,"call_of_yucutan:ritual_rock_pillar":5,"graveyard:dark_iron_door":1,"minecraft:wither_skeleton_skull":2,"minecraft:lapis_lazuli":25,"minecraft:dirt":330,"minecraft:name_tag":1,"brewery:hops_seeds":10,"minecraft:leather_boots":5,"redeco:spyglass_stand":2,"minecraft:bone":61,"irons_spellbooks:hogskin":1,"minecraft:bow":4,"minecraft:wheat_seeds":24,"minecraft:orange_tulip":2,"minecraft:cobbled_deepslate_slab":13,"minecraft:deepslate_brick_slab":6,"minecraft:raw_gold":59,"call_of_yucutan:golden_torch":5,"camera:image":27,"minecraft:oak_planks":59,"irons_spellbooks:firefly_jar":1,"samurai_dynasty:tanuki_statue":2,"brewery:beer_hops":1,"bakery:bun":5,"irons_spellbooks:fireward_ring":8,"minecraft:cooked_porkchop":5,"irons_spellbooks:frozen_bone":5,"graveyard:bone_dagger":1,"minecraft:poisonous_potato":1,"vampirism:crucifix_normal":1,"minecraft:sand":27,"minecraft:grass_block":4,"securitycraft:reinforced_stone":16,"minecraft:lily_of_the_valley":1,"minecraft:cyan_bed":1,"call_of_yucutan:elder_bone":42,"call_of_yucutan:ancient_gold":3,"minecraft:yellow_carpet":3,"minecraft:diamond":50,"minecraft:slime_block":2,"minecraft:soul_lantern":3,"waystones:waystone":14,"minecraft:cracked_polished_blackstone_bricks":4,"bakery:tray":1,"minecraft:emerald":52,"werewolves:cracked_bone":2,"biomesoplenty:pink_daffodil":4,"minecraft:oak_sapling":66,"minecraft:netherrack":66,"minecraft:allium":8,"minecraft:azure_bluet":6,"artifacts:night_vision_goggles":6,"minecraft:chicken":3,"minecraft:ladder":9,"farmersdelight:sweet_berry_cheesecake_slice":3,"minecraft:chest_minecart":2,"minecraft:brown_mushroom":66,"minecraft:gold_block":2,"bakery:strawberry_glazed_cookie":3,"call_of_yucutan:ancient_gold_pillar":3,"alexscaves:flood_basalt":5,"minecraft:chain":5,"ribbits:mossy_oak_planks_slab":4,"minecraft:brick":4,"bakery:sweetberry_cake_slice":3,"minecraft:shield":1,"alexscaves:dinosaur_nugget":46,"minecraft:oak_trapdoor":5,"minecraft:moss_carpet":3,"minecraft:iron_axe":3,"minecraft:wooden_sword":1,"minecraft:item_frame":4,"alexscaves:dinosaur_chop":2,"graveyard:corruption":29,"irons_spellbooks:conjurers_talisman":1,"minecraft:candle":30,"minecraft:echo_shard":3,"minecraft:oak_boat":2,"irons_spellbooks:epic_ink":7,"redeco:crimson_display_case":4,"irons_spellbooks:lightning_bottle":2,"minecraft:sugar_cane":3,"samurai_dynasty:aquamarine":2,"minecraft:phantom_membrane":3,"ribbits:mossy_oak_door":4,"farmersdelight:kelp_roll_slice":1,"minecraft:raw_iron":243,"bakery:croissant":5,"minecraft:copper_ingot":1,"minecraft:note_block":1,"artifacts:vampiric_glove":9,"bakery:chocolate_gateau_slice":3,"irons_spellbooks:oakskin_elixir":2,"irons_spellbooks:mana_ring":17,"artifacts:snorkel":7,"minecraft:arrow":20,"biomesoplenty:cattail":4,"stalwart_dungeons:raw_tungsten":1,"alexscaves:pewen_wood":13,"relics:spatial_sign":2,"mowziesmobs:ice_crystal":1,"artifacts:running_shoes":2,"bakery:apple_cupcake":10,"alexsmobs:ghostly_pickaxe":1,"securitycraft:keypad_door_item":1,"minecraft:cracked_deepslate_tiles":23,"samurai_dynasty:kitsune_tail":2,"minecraft:crimson_stem":3,"samurai_dynasty:ruby":1,"minecraft:golden_carrot":7,"minecraft:glow_ink_sac":13,"minecraft:salmon":6,"minecraft:leather":37,"minecraft:music_disc_stal":2,"minecraft:birch_planks":12,"alexscaves:limestone":154,"call_of_yucutan:ritual_rocks":14,"minecraft:crimson_fungus":1,"bakery:sweetberry_cupcake":6,"minecraft:nether_wart_block":20,"minecraft:cobblestone_wall":2,"minecraft:yellow_bed":5,"minecraft:gunpowder":17,"minecraft:deepslate_tile_slab":49,"legendary_monsters:frozen_rune":1,"irons_spellbooks:rare_ink":7,"alexscaves:amber":18,"minecraft:cooked_mutton":10,"farmersdelight:honey_glazed_ham_block":2,"minecraft:red_carpet":2,"minecraft:gray_carpet":73,"minecraft:iron_ingot":35,"minecraft:cooked_chicken":1,"minecraft:stripped_oak_wood":3,"alexscaves:curly_fern":1,"vampirism:altar_cleansing":2,"farmersdelight:dumplings":1,"minecraft:soul_sand":9,"sophisticatedbackpacks:blasting_upgrade":1,"sophisticatedbackpacks:diamond_backpack":15,"minecraft:book":40,"stalwart_dungeons:transient_block_close":4,"minecraft:sculk_catalyst":2,"slashblade:proudsoul_tiny":2,"minecraft:warped_fungus":1,"moneyforeveryone:coin_copper":3,"minecraft:dandelion":7,"call_of_yucutan:solar_projector":1,"minecraft:raw_iron_block":1,"minecraft:dripstone_block":13,"minecraft:amethyst_shard":51,"minecraft:blast_furnace":6,"vampirism:altar_infusion":1,"call_of_yucutan:red_limestone_tiles":7,"minecraft:spruce_door":1,"bakery:cupcake_display":4,"minecraft:green_carpet":1,"minecraft:spider_eye":12,"alexsmobs:raw_catfish":48,"minecraft:pumpkin_seeds":9,"samurai_dynasty:spirit_stone_base":1,"vampirism:altar_tip":4,"call_of_yucutan:ritual_rock_tiles":3,"minecraft:iron_helmet":6,"call_of_yucutan:ancient_gold_ingot":2,"irons_spellbooks:netherward_tincture":7,"minecraft:cherry_sapling":1,"minecraft:mossy_cobblestone_stairs":1,"minecraft:damaged_anvil":3,"securitycraft:door_indestructible_iron_item":2,"minecraft:black_wool":2,"minecraft:coal":239},"minecraft:dropped":{"minecraft:iron_sword":3,"call_of_yucutan:elder_bone":30,"minecraft:porkchop":3,"minecraft:cooked_beef":43,"minecraft:glow_ink_sac":3,"minecraft:glass_bottle":5,"minecraft:diamond":31,"minecraft:crafting_table":1,"minecraft:cooked_porkchop":2,"mowziesmobs:ice_crystal":1,"minecraft:glow_item_frame":1,"minecraft:warped_roots":1,"bakery:misslilitu_biscuit":2,"minecraft:black_bed":1,"call_of_yucutan:ritual_rock_pillar":1,"alexscaves:pewen_log":171,"samurai_dynasty:spirit_upgrade_smithing_template":3,"minecraft:leather_helmet":1,"minecraft:red_mushroom":2,"sophisticatedbackpacks:gold_backpack":1,"minecraft:emerald":2,"minecraft:dirt":32,"bakery:cornet":7,"minecraft:dark_oak_trapdoor":1,"irons_spellbooks:arcane_essence":1,"alexscaves:dinosaur_nugget":68,"bakery:jam_roll":2,"minecraft:sand":1,"minecraft:iron_pickaxe":3,"vanillaplustools:iron_hammer":2,"minecraft:music_disc_stal":1,"vampirism:altar_infusion":1,"call_of_yucutan:ritual_rock_tiles":2,"minecraft:stone_axe":1,"artifacts:power_glove":3,"minecraft:iron_nugget":29,"minecraft:cobbled_deepslate":38,"moneyforeveryone:coin_copper":1,"minecraft:nether_brick":6,"minecraft:birch_sapling":2,"minecraft:wheat":1,"minecraft:stripped_dark_oak_log":2,"camera:image":23,"minecraft:rotten_flesh":4,"aquamirae:coral_lance":2,"minecraft:oak_planks":2,"minecraft:enchanted_golden_apple":1,"minecraft:glowstone_dust":3,"irons_spellbooks:inscription_table":3,"minecraft:salmon":20,"vampirism:vampire_blood_bottle":4,"vampirism:vampire_fang":6,"farmersdelight:honey_glazed_ham_block":1,"minecraft:leather_boots":1,"minecraft:ladder":4,"minecraft:leather_leggings":1,"minecraft:beef":16,"vampirism:blood_container":1,"irons_spellbooks:cast_time_ring":1,"slashblade:proudsoul_tiny":2,"minecraft:egg":2,"minecraft:enchanted_book":3,"farmersdelight:tomato_seeds":5,"minecraft:iron_ingot":101,"minecraft:wheat_seeds":5,"vampirism:dark_stone_bricks":2,"minecraft:iron_helmet":2,"minecraft:cobblestone":918,"minecraft:book":1,"relics:midnight_robe":1,"minecraft:apple":63,"minecraft:granite":31,"brewery:corn_seeds":2,"minecraft:coal":7,"alexsmobs:raw_catfish":6,"minecraft:cobweb":14,"bakery:apple_cupcake":2,"minecraft:diamond_helmet":2,"minecraft:potion":3,"alexsmobs:ghostly_pickaxe":1,"minecraft:mossy_cobblestone_stairs":1,"farmersdelight:roast_chicken_block":1,"minecraft:paper":23,"minecraft:string":11,"minecraft:spruce_sapling":1,"camera:image_frame":1,"farmersdelight:kelp_roll_slice":3,"minecraft:clay_ball":2,"minecraft:iron_boots":3,"sophisticatedbackpacks:backpack":6,"call_of_yucutan:huracan_helmet":1,"minecraft:shears":1,"irons_spellbooks:pyromancer_boots":2,"minecraft:allium":3,"minecraft:spruce_planks":1,"minecraft:diamond_pickaxe":1,"irons_spellbooks:mana_ring":2,"minecraft:brown_bed":1,"minecraft:spider_eye":3,"irons_spellbooks:iron_spell_book":5,"relics:arrow_quiver":1,"farmersdelight:sweet_berry_cheesecake_slice":2,"minecraft:black_wool":1,"irons_spellbooks:netherward_tincture":2,"minecraft:moss_block":2,"minecraft:brown_mushroom":3,"biomesoplenty:pink_daffodil":1,"irons_spellbooks:artificer_cane":1,"minecraft:oak_log":16,"minecraft:golden_pickaxe":1,"minecraft:ender_pearl":2,"vampirism:altar_tip":4,"irons_spellbooks:pyromancer_helmet":2,"relics:horse_flute":1,"minecraft:cod":15,"samurai_dynasty:kitsune_hide":1,"artifacts:night_vision_goggles":1,"farmersdelight:salmon_roll":4,"minecraft:cracked_polished_blackstone_bricks":1,"minecraft:netherite_scrap":1,"vampirism:altar_pillar":12,"irons_spellbooks:pyromancer_leggings":3,"alexsmobs:cooked_catfish":3,"gravestone:obituary":74,"farmersdelight:onion":36,"call_of_yucutan:ancient_gold_ingot":1,"irons_spellbooks:shriving_stone":1,"irons_spellbooks:pyromancer_chestplate":2,"bakery:croissant":2,"minecraft:gravel":2,"beautify:lamp_jar":2,"minecraft:pointed_dripstone":4,"vampirism:holy_water_bottle_enhanced":1,"vampirism:blood_bottle":7,"minecraft:cooked_mutton":8,"alexscaves:pewen_wood":12,"minecraft:carrot":13,"sophisticatedbackpacks:blasting_upgrade":1,"minecraft:poppy":1,"minecraft:gunpowder":4,"irons_spellbooks:greater_invisibility_elixir":1,"minecraft:melon_seeds":2,"minecraft:chest":2,"minecraft:iron_bars":12,"minecraft:arrow":3,"relics:spatial_sign":1,"call_of_yucutan:ritual_rocks":11,"minecraft:written_book":1,"minecraft:netherrack":1,"minecraft:firework_rocket":22,"minecraft:bread":55,"minecraft:diamond_leggings":1,"call_of_yucutan:blow_gun":3,"minecraft:lead":1,"call_of_yucutan:poisonous_dart":6,"bakery:sweetberry_cupcake":1,"minecraft:grass_block":3,"minecraft:stick":22,"irons_spellbooks:scroll":9,"minecraft:diorite":6,"minecraft:torch":116,"minecraft:iron_leggings":3,"minecraft:iron_axe":1,"brewery:beer_mug":1,"minecraft:smooth_basalt":1,"minecraft:redstone":1,"samurai_dynasty:spirit_stone_base":1,"minecraft:sweet_berries":2,"minecraft:oak_trapdoor":2,"vampirism:obi_belt":1,"farmersdelight:dumplings":1,"minecraft:iron_hoe":1,"bakery:waffle":1,"minecraft:filled_map":1,"relics:magic_mirror":1,"minecraft:diamond_chestplate":1,"irons_spellbooks:wandering_magician_leggings":1,"minecraft:iron_chestplate":5,"minecraft:andesite":6,"minecraft:oak_boat":1,"minecraft:oak_sapling":11,"brewery:hops_seeds":2,"minecraft:wooden_pickaxe":1,"minecraft:raw_gold":22,"minecraft:calcite":4,"minecraft:brick":4},"minecraft:killed":{"vampirism:vampire":13,"minecraft:cave_spider":6,"vampirism:advanced_vampire":6,"irons_spellbooks:cryomancer":1,"alexsmobs:shoebill":2,"graveyard:wraith":52,"minecraft:skeleton":52,"vampirism:blinding_bat":4,"werewolves:werewolf_beast":1,"graveyard:acolyte":48,"irons_spellbooks:apothecarist":3,"minecraft:chicken":2,"minecraft:magma_cube":7,"stalwart_dungeons:giddy_blaze":7,"minecraft:iron_golem":2,"call_of_yucutan:undead_warrior":6,"minecraft:pillager":6,"minecraft:zombie":104,"stalwart_dungeons:incomplete_wither":4,"minecraft:cow":23,"graveyard:corrupted_vindicator":20,"minecraft:vindicator":1,"alexsmobs:seagull":1,"legendary_monsters:frostbitten_golem":1,"stalwart_dungeons:nether_wart_cocoon":6,"alexsmobs:underminer":1,"minecraft:warden":2,"goblintraders:goblin_trader":1,"graveyard:ghoul":4,"alexsmobs:catfish":21,"alexsmobs:crocodile":1,"alexscaves:grottoceratops":13,"minecraft:enderman":8,"minecraft:witch":1,"graveyard:skeleton_creeper":4,"alexsmobs:anaconda":1,"irons_spellbooks:pyromancer":2,"minecraft:spider":31,"irons_spellbooks:summoned_skeleton":5,"artifacts:mimic":1,"minecraft:wolf":2,"samurai_dynasty:kitsune":2,"minecraft:piglin":7,"minecraft:pig":4,"minecraft:zombie_villager":3,"samurai_dynasty:akaname":1,"irons_spellbooks:necromancer":6,"minecraft:creeper":27,"alexsmobs:crimson_mosquito":8,"vampirism:hunter":1,"alexsmobs:warped_toad":1,"minecraft:sheep":18,"minecraft:ghast":1,"alexsmobs:fly":4,"graveyard:corrupted_pillager":9,"alexscaves:vallumraptor":9,"samurai_dynasty:jorogumo":3,"alexscaves:tremorsaurus":5,"irons_spellbooks:summoned_zombie":7,"minecraft:slime":31,"minecraft:phantom":6,"alexsmobs:bison":2,"minecraft:drowned":2,"alexscaves:relicheirus":4,"mowziesmobs:grottol":2,"call_of_yucutan:blowgun_huracan":16,"stalwart_dungeons:reinforced_blaze":2,"samurai_dynasty:oni":1,"minecraft:hoglin":7,"alexscaves:subterranodon":4},"minecraft:mined":{"call_of_yucutan:bone_torch_wall":1,"graveyard:gray_urn":1,"minecraft:jungle_leaves":25,"minecraft:red_nether_bricks":1,"minecraft:obsidian":10,"alexscaves:limestone":160,"minecraft:granite":238,"minecraft:yellow_carpet":1,"call_of_yucutan:golden_torch_wall":8,"redeco:spruce_coffee_table":1,"minecraft:jungle_log":2,"minecraft:coal_block":13,"minecraft:deepslate_bricks":101,"minecraft:blue_wool":39,"biomesoplenty:cattail":4,"minecraft:crimson_fungus":1,"minecraft:spawner":19,"minecraft:weeping_vines_plant":1,"minecraft:tall_seagrass":22,"graveyard:wither_skull_with_rib_cage":1,"minecraft:magma_block":10,"minecraft:mossy_cobblestone_stairs":1,"minecraft:dark_oak_trapdoor":1,"minecraft:sticky_piston":1,"minecraft:cobbled_deepslate":11,"minecraft:barrel":2,"minecraft:fire":18,"biomesoplenty:lavender":1,"minecraft:moss_carpet":1,"minecraft:deepslate_lapis_ore":4,"minecraft:sculk_shrieker":24,"minecraft:polished_deepslate_slab":13,"biomesoplenty:webbing":212,"minecraft:oak_stairs":2,"minecraft:deepslate_brick_stairs":9,"minecraft:tripwire":1,"minecraft:blue_wall_banner":1,"samurai_dynasty:spirit_stone_base":1,"minecraft:brown_mushroom":3,"alexscaves:amber":18,"brewery:wild_hops":5,"minecraft:red_bed":5,"biomesoplenty:glowworm_silk":2,"minecraft:smoker":1,"alexscaves:cave_painting_grottoceratops":1,"minecraft:deepslate_tile_slab":56,"graveyard:fire_brazier":6,"minecraft:amethyst_cluster":2,"minecraft:powder_snow":12,"minecraft:torch":5,"minecraft:note_block":3,"minecraft:blast_furnace":6,"minecraft:melon":3,"minecraft:cyan_bed":1,"minecraft:damaged_anvil":10,"minecraft:amethyst_block":3,"minecraft:chain":5,"minecraft:cyan_wool":39,"graveyard:wither_skeleton_hand":1,"refurbished_furniture:oak_hedge":1,"minecraft:mud":1,"sophisticatedbackpacks:diamond_backpack":3,"minecraft:wheat":79,"minecraft:lilac":5,"minecraft:jukebox":1,"minecraft:black_bed":9,"minecraft:warped_fungus":1,"minecraft:grass":220,"minecraft:loom":2,"minecraft:smooth_basalt":5,"minecraft:stonecutter":1,"minecraft:deepslate":1923,"biomesoplenty:reed":3,"alexscaves:flood_basalt":5,"minecraft:deepslate_tiles":28,"call_of_yucutan:reflector":1,"biomesoplenty:watergrass":42,"minecraft:light_blue_wool":40,"alexscaves:primal_magma":22,"minecraft:light_gray_stained_glass_pane":2,"samurai_dynasty:deepslate_aquamarine_ore":2,"ribbits:mossy_oak_planks_slab":4,"farmersdelight:wild_carrots":4,"minecraft:cobbled_deepslate_slab":17,"redeco:crimson_display_case":4,"call_of_yucutan:overgrown_chest":3,"minecraft:spruce_fence":19,"minecraft:jungle_planks":1,"minecraft:crimson_roots":2,"graveyard:tg_deepslate":1,"minecraft:redstone_wire":7,"minecraft:moss_block":9,"farmersdelight:wild_onions":1,"minecraft:redstone_ore":1,"minecraft:packed_mud":3,"graveyard:tg_moss_block":2,"minecraft:suspicious_sand":1,"minecraft:andesite":22,"call_of_yucutan:ancient_gold_pillar":3,"minecraft:potatoes":5,"biomesoplenty:high_grass":59,"minecraft:vine":3,"bakery:crusty_bread_block":1,"biomesoplenty:barley":39,"irons_spellbooks:inscription_table":13,"minecraft:white_wool":64,"minecraft:cake":1,"minecraft:smithing_table":2,"bakery:cake_stand":2,"minecraft:glass_pane":2,"minecraft:cherry_planks":5,"bakery:breadbox":3,"minecraft:soul_sand":9,"call_of_yucutan:red_limestone_tiles":8,"minecraft:dandelion":7,"minecraft:cornflower":2,"minecraft:emerald_ore":1,"biomesoplenty:high_grass_plant":139,"minecraft:copper_ore":119,"minecraft:tall_grass":41,"minecraft:deepslate_gold_ore":24,"minecraft:cracked_deepslate_bricks":8,"minecraft:diorite":107,"stalwart_dungeons:tungsten_ore":2,"beautify:lamp_jar":2,"minecraft:purple_bed":5,"minecraft:red_terracotta":1,"minecraft:coarse_dirt":1,"redeco:sculk_terrarium":2,"biomesoplenty:snowblossom_sapling":1,"graveyard:vase_block":31,"minecraft:cobblestone_wall":2,"minecraft:white_carpet":1,"minecraft:spruce_log":46,"minecraft:birch_leaves":4,"minecraft:mycelium":1,"werewolves:deepslate_silver_ore":23,"vampirism:fire_place":2,"minecraft:gravel":3,"minecraft:dripstone_block":11,"biomesoplenty:stringy_cobweb":1,"minecraft:cobweb":117,"minecraft:polished_blackstone":1,"minecraft:stone_bricks":128,"minecraft:gold_ore":1,"minecraft:fern":47,"minecraft:spruce_planks":51,"bakery:cupcake_display":4,"farmersdelight:roast_chicken_block":1,"minecraft:sculk_vein":56,"minecraft:cobblestone_stairs":1,"sophisticatedbackpacks:gold_backpack":5,"irons_spellbooks:arcane_anvil":3,"minecraft:brewing_stand":2,"minecraft:spruce_trapdoor":2,"minecraft:cave_vines_plant":1,"minecraft:grass_block":237,"minecraft:cracked_polished_blackstone_bricks":3,"graveyard:dark_iron_door":1,"minecraft:mud_bricks":10,"minecraft:composter":1,"irons_spellbooks:scroll_forge":7,"minecraft:raw_iron_block":1,"bakery:cake_display":5,"minecraft:sculk_catalyst":2,"minecraft:iron_ore":175,"graveyard:leaning_wither_skeleton":1,"minecraft:target":1,"minecraft:anvil":2,"minecraft:brown_bed":1,"vampirism:tent":4,"alexscaves:amber_monolith":7,"minecraft:azure_bluet":3,"biomesoplenty:hanging_cobweb":2,"minecraft:pointed_dripstone":6,"minecraft:iron_bars":13,"graveyard:small_brown_urn":1,"call_of_yucutan:polished_jade_block":1,"graveyard:wither_skull_pile":1,"alexscaves:limestone_pillar":4,"minecraft:spruce_slab":15,"minecraft:green_bed":8,"call_of_yucutan:golden_torch_ground":1,"minecraft:deepslate_redstone_ore":39,"minecraft:polished_deepslate_stairs":2,"irons_spellbooks:alchemist_cauldron":21,"stalwart_dungeons:transient_block_close":4,"minecraft:soul_lantern":3,"minecraft:clay":1,"minecraft:calcite":5,"minecraft:poppy":3,"minecraft:chest":24,"minecraft:mushroom_stem":5,"minecraft:cobblestone":99,"graveyard:skeleton_hand":1,"minecraft:slime_block":2,"graveyard:lying_skeleton":3,"minecraft:wall_torch":9,"minecraft:oak_planks":49,"minecraft:iron_door":5,"call_of_yucutan:mystic_vine_block":5,"minecraft:deepslate_copper_ore":6,"minecraft:seagrass":5,"minecraft:dark_oak_slab":2,"minecraft:dark_oak_door":1,"minecraft:nether_wart_block":1,"minecraft:birch_log":29,"call_of_yucutan:red_limestone":5,"samurai_dynasty:deepslate_jade_ore":4,"minecraft:stripped_oak_wood":3,"graveyard:skull_pile":1,"mcwfurnitures:oak_modern_chair":1,"call_of_yucutan:ritual_rocks":3,"minecraft:cracked_deepslate_tiles":6,"biomesoplenty:clover":15,"minecraft:oak_log":33,"minecraft:dirt":85,"minecraft:sand":29,"call_of_yucutan:ritual_rock_tiles":3,"minecraft:raw_copper_block":2,"minecraft:netherrack":78,"minecraft:ancient_debris":3,"minecraft:oak_leaves":12,"werewolves:silver_ore":7,"minecraft:gray_candle":1,"minecraft:crying_obsidian":4,"vampirism:dark_stone_bricks":5,"farmersdelight:honey_glazed_ham_block":1,"minecraft:tuff":242,"minecraft:red_carpet":2,"minecraft:deepslate_diamond_ore":39,"minecraft:candle":1,"minecraft:red_stained_glass":2,"minecraft:ladder":1,"gravestone:gravestone":99,"biomesoplenty:bush":17,"minecraft:decorated_pot":1,"minecraft:weeping_vines":1,"minecraft:white_stained_glass":2,"minecraft:brown_mushroom_block":1,"bakery:toast_block":1,"minecraft:spruce_leaves":136,"minecraft:sandstone":15,"minecraft:large_fern":17,"minecraft:hay_block":26,"graveyard:soul_fire_brazier":2,"minecraft:deepslate_brick_slab":2,"alexscaves:subterranodon_egg":3,"minecraft:oak_trapdoor":1,"minecraft:spruce_sapling":4,"minecraft:furnace":9,"minecraft:chiseled_deepslate":4,"treechop:chopped_log":74,"samurai_dynasty:tanuki_statue":2,"redeco:spyglass_stand":3,"elevatorid:elevator_gray":2,"minecraft:polished_deepslate":8,"minecraft:bookshelf":15,"minecraft:deepslate_iron_ore":65,"ribbits:mossy_oak_door":4,"minecraft:lantern":5,"minecraft:stripped_oak_log":13,"alexscaves:curly_fern":1,"irons_spellbooks:firefly_jar":1,"biomesoplenty:spider_egg":1,"minecraft:stone":3127,"call_of_yucutan:ancient_gold":3,"minecraft:acacia_leaves":2,"minecraft:stripped_dark_oak_log":30,"minecraft:spruce_door":1,"graveyard:small_light_gray_urn":12,"minecraft:oak_fence":11,"minecraft:crafting_table":4,"biomesoplenty:snowblossom_leaves":35,"minecraft:rose_bush":1,"minecraft:sculk_sensor":26,"redeco:spruce_chair":1,"graveyard:tg_grass_block":2,"biomesoplenty:huge_clover_petal":8,"minecraft:lily_pad":3,"vampirism:cracked_dark_stone_bricks":1,"minecraft:sculk":128,"minecraft:blue_bed":2,"minecraft:spruce_stairs":41,"minecraft:gray_wool":105,"biomesoplenty:red_maple_leaf_pile":1,"minecraft:sweet_berry_bush":18,"biomesoplenty:pink_daffodil":2,"minecraft:bee_nest":1,"minecraft:yellow_bed":4,"elevatorid:elevator_white":5,"graveyard:dark_iron_bars":1,"minecraft:coal_ore":121,"graveyard:leaning_skeleton":1,"call_of_yucutan:ritual_rock_pillar":7,"minecraft:gray_carpet":70,"minecraft:polished_andesite":1,"minecraft:mossy_stone_bricks":1},"minecraft:custom":{"minecraft:interact_with_crafting_table":67,"minecraft:open_barrel":284,"goblintraders:trade_with_goblin":395,"minecraft:eat_cake_slice":7,"minecraft:leave_game":204,"minecraft:time_since_death":60892,"minecraft:damage_blocked_by_shield":7039,"vampirism:interact_with_coffin":2,"minecraft:play_time":2470265,"minecraft:deaths":111,"minecraft:jump":31099,"minecraft:interact_with_furnace":91,"minecraft:play_record":2,"minecraft:traded_with_villager":16,"minecraft:sleep_in_bed":31,"minecraft:waystone_activated":18,"minecraft:damage_dealt":55479,"minecraft:interact_with_smoker":1,"minecraft:horse_one_cm":84213,"minecraft:use_cauldron":1,"minecraft:interact_with_anvil":29,"minecraft:damage_dealt_absorbed":165,"minecraft:sneak_time":126696,"minecraft:interact_with_lectern":12,"minecraft:interact_with_blast_furnace":7,"minecraft:total_world_time":2470265,"minecraft:tune_noteblock":1,"vampirism:interact_with_garlic_diffuser":1,"minecraft:interact_with_stonecutter":8,"minecraft:time_since_rest":60931,"minecraft:swim_one_cm":889817,"minecraft:fly_one_cm":4323734,"minecraft:open_chest":973,"minecraft:fall_one_cm":939486,"minecraft:animals_bred":3,"minecraft:damage_resisted":122,"minecraft:sprint_one_cm":5796245,"minecraft:drop":862,"minecraft:talked_to_villager":10,"minecraft:play_noteblock":4,"minecraft:interact_with_brewingstand":4,"minecraft:walk_on_water_one_cm":387128,"vampirism:altar_of_inspiration_rituals_performed":3,"vampirism:interact_with_research_table":2,"minecraft:interact_with_loom":31,"minecraft:player_kills":12,"minecraft:crouch_one_cm":444308,"minecraft:mob_kills":704,"minecraft:damage_dealt_resisted":523,"minecraft:climb_one_cm":121638,"minecraft:walk_one_cm":7317562,"vampirism:skills_unlocked":2,"minecraft:walk_under_water_one_cm":190119,"minecraft:boat_one_cm":743676,"minecraft:raid_trigger":1,"minecraft:pot_flower":1,"minecraft:damage_taken":241245,"minecraft:damage_absorbed":865,"minecraft:trigger_trapped_chest":2,"minecraft:aviate_one_cm":7478393},"minecraft:killed_by":{"graveyard:acolyte":4,"minecraft:vindicator":1,"samurai_dynasty:jorogumo":2,"minecraft:zombie":5,"vampirism:vampire":1,"alexsmobs:rocky_roller":1,"minecraft:warden":22,"irons_spellbooks:apothecarist":2,"irons_spellbooks:cryomancer":2,"minecraft:creeper":6,"alexsmobs:murmur_head":2,"alexsmobs:tusklin":1,"graveyard:skeleton_creeper":1,"call_of_yucutan:blowgun_huracan":1,"alexsmobs:crocodile":2,"cataclysm:deepling_brute":1,"minecraft:witch":1,"werewolves:werewolf_beast":3,"graveyard:wraith":5,"call_of_yucutan:undead_warrior":1,"minecraft:player":4,"minecraft:enderman":1,"samurai_dynasty:onibi":1,"irons_spellbooks:necromancer":3,"minecraft:skeleton":5,"graveyard:corrupted_vindicator":5,"werewolves:werewolf_survivalist":2},"minecraft:broken":{"minecraft:shears":1,"minecraft:iron_boots":2,"minecraft:iron_chestplate":1,"irons_spellbooks:wandering_magician_leggings":1,"minecraft:iron_leggings":1,"minecraft:golden_sword":1,"irons_spellbooks:wandering_magician_boots":1,"minecraft:iron_sword":2,"irons_spellbooks:pyromancer_boots":1,"minecraft:shield":3,"irons_spellbooks:wandering_magician_chestplate":1,"minecraft:iron_axe":3,"minecraft:iron_pickaxe":4,"minecraft:iron_helmet":1,"minecraft:golden_shovel":1,"irons_spellbooks:wandering_magician_helmet":1}},"DataVersion":3465}